{"inputs":{"app/entry.server.tsx":{"bytes":2927,"imports":[{"path":"node:stream","kind":"import-statement","external":true},{"path":"@remix-run/node","kind":"import-statement","external":true},{"path":"@remix-run/react","kind":"import-statement","external":true},{"path":"isbot","kind":"import-statement","external":true},{"path":"react-dom/server","kind":"import-statement","external":true},{"path":"react/jsx-dev-runtime","kind":"import-statement","external":true}],"format":"esm"},"app/tailwind.css":{"bytes":11727,"imports":[]},"app/root.tsx":{"bytes":823,"imports":[{"path":"@remix-run/react","kind":"import-statement","external":true},{"path":"app/tailwind.css","kind":"import-statement","original":"~/tailwind.css"},{"path":"react/jsx-dev-runtime","kind":"import-statement","external":true}],"format":"esm"},"app/routes/login/components/form-field.tsx":{"bytes":1082,"imports":[{"path":"react","kind":"import-statement","external":true},{"path":"react/jsx-dev-runtime","kind":"import-statement","external":true}],"format":"esm"},"app/components/home/portal.tsx":{"bytes":950,"imports":[{"path":"react-dom","kind":"import-statement","external":true},{"path":"react","kind":"import-statement","external":true}],"format":"esm"},"app/components/home/modal.tsx":{"bytes":957,"imports":[{"path":"app/components/home/portal.tsx","kind":"import-statement","original":"./portal"},{"path":"@remix-run/react","kind":"import-statement","external":true},{"path":"react/jsx-dev-runtime","kind":"import-statement","external":true}],"format":"esm"},"app/utils/prisma.server.ts":{"bytes":377,"imports":[{"path":"@prisma/client","kind":"import-statement","external":true}],"format":"esm"},"app/utils/link.server.ts":{"bytes":842,"imports":[{"path":"app/utils/prisma.server.ts","kind":"import-statement","original":"./prisma.server"}],"format":"esm"},"app/routes/home/link.$linkId.tsx":{"bytes":624,"imports":[{"path":"@remix-run/node","kind":"import-statement","external":true},{"path":"@remix-run/react","kind":"import-statement","external":true},{"path":"app/components/home/modal.tsx","kind":"import-statement","original":"~/components/home/modal"},{"path":"app/utils/link.server.ts","kind":"import-statement","original":"~/utils/link.server"},{"path":"react/jsx-dev-runtime","kind":"import-statement","external":true}],"format":"esm"},"app/components/layout.tsx":{"bytes":230,"imports":[{"path":"react/jsx-dev-runtime","kind":"import-statement","external":true}],"format":"esm"},"app/utils/user.server.ts":{"bytes":1636,"imports":[{"path":"app/utils/prisma.server.ts","kind":"import-statement","original":"./prisma.server"},{"path":"bcryptjs","kind":"import-statement","external":true}],"format":"esm"},"app/utils/auth.server.ts":{"bytes":3812,"imports":[{"path":"app/utils/prisma.server.ts","kind":"import-statement","original":"./prisma.server"},{"path":"@remix-run/node","kind":"import-statement","external":true},{"path":"app/utils/user.server.ts","kind":"import-statement","original":"./user.server"},{"path":"bcryptjs","kind":"import-statement","external":true}],"format":"esm"},"app/utils/validators.server.ts":{"bytes":2149,"imports":[],"format":"esm"},"app/components/logo.tsx":{"bytes":177,"imports":[{"path":"react/jsx-dev-runtime","kind":"import-statement","external":true}],"format":"esm"},"app/routes/login/index.tsx":{"bytes":6255,"imports":[{"path":"react","kind":"import-statement","external":true},{"path":"app/components/layout.tsx","kind":"import-statement","original":"~/components/layout"},{"path":"app/routes/login/components/form-field.tsx","kind":"import-statement","original":"~/routes/login/components/form-field"},{"path":"@remix-run/react","kind":"import-statement","external":true},{"path":"@remix-run/node","kind":"import-statement","external":true},{"path":"app/utils/auth.server.ts","kind":"import-statement","original":"~/utils/auth.server"},{"path":"app/utils/validators.server.ts","kind":"import-statement","original":"~/utils/validators.server"},{"path":"app/components/logo.tsx","kind":"import-statement","original":"~/components/logo"},{"path":"react/jsx-dev-runtime","kind":"import-statement","external":true}],"format":"esm"},"app/routes/home/index.tsx":{"bytes":5334,"imports":[{"path":"@remix-run/node","kind":"import-statement","external":true},{"path":"react","kind":"import-statement","external":true},{"path":"app/components/layout.tsx","kind":"import-statement","original":"~/components/layout"},{"path":"tailwindcss/colors","kind":"import-statement","external":true},{"path":"app/utils/user.server.ts","kind":"import-statement","original":"~/utils/user.server"},{"path":"app/utils/link.server.ts","kind":"import-statement","original":"~/utils/link.server"},{"path":"app/utils/auth.server.ts","kind":"import-statement","original":"~/utils/auth.server"},{"path":"@remix-run/react","kind":"import-statement","external":true},{"path":"app/utils/validators.server.ts","kind":"import-statement","original":"~/utils/validators.server"},{"path":"app/components/logo.tsx","kind":"import-statement","original":"~/components/logo"},{"path":"react/jsx-dev-runtime","kind":"import-statement","external":true}],"format":"esm"},"app/routes/$username.tsx":{"bytes":1883,"imports":[{"path":"@remix-run/node","kind":"import-statement","external":true},{"path":"@remix-run/node","kind":"import-statement","external":true},{"path":"@remix-run/react","kind":"import-statement","external":true},{"path":"react-icons/ri","kind":"import-statement","external":true},{"path":"tailwindcss/colors","kind":"import-statement","external":true},{"path":"app/components/logo.tsx","kind":"import-statement","original":"~/components/logo"},{"path":"app/utils/user.server.ts","kind":"import-statement","original":"~/utils/user.server"},{"path":"react/jsx-dev-runtime","kind":"import-statement","external":true}],"format":"esm"},"app/routes/logout.tsx":{"bytes":306,"imports":[{"path":"@remix-run/node","kind":"import-statement","external":true},{"path":"app/utils/auth.server.ts","kind":"import-statement","original":"~/utils/auth.server"}],"format":"esm"},"app/routes/error.tsx":{"bytes":174,"imports":[{"path":"@remix-run/node","kind":"import-statement","external":true}],"format":"esm"},"app/components/sign-out-button.tsx":{"bytes":411,"imports":[{"path":"react/jsx-dev-runtime","kind":"import-statement","external":true}],"format":"esm"},"app/routes/index.tsx":{"bytes":2014,"imports":[{"path":"@remix-run/node","kind":"import-statement","external":true},{"path":"@remix-run/react","kind":"import-statement","external":true},{"path":"app/components/layout.tsx","kind":"import-statement","original":"~/components/layout"},{"path":"app/utils/auth.server.ts","kind":"import-statement","original":"~/utils/auth.server"},{"path":"app/components/sign-out-button.tsx","kind":"import-statement","original":"../components/sign-out-button"},{"path":"react-icons/ri","kind":"import-statement","external":true},{"path":"react/jsx-dev-runtime","kind":"import-statement","external":true}],"format":"esm"},"server-assets-manifest:@remix-run/dev/assets-manifest":{"bytes":3332,"imports":[],"format":"esm"},"server-entry-module:@remix-run/dev/server-build":{"bytes":2688,"imports":[{"path":"app/entry.server.tsx","kind":"import-statement","original":"/Users/connorswis/Documents/GitHub/find-me/app/entry.server.tsx"},{"path":"app/root.tsx","kind":"import-statement","original":"./root.tsx"},{"path":"app/routes/login/components/form-field.tsx","kind":"import-statement","original":"./routes/login/components/form-field.tsx"},{"path":"app/routes/home/link.$linkId.tsx","kind":"import-statement","original":"./routes/home/link.$linkId.tsx"},{"path":"app/routes/login/index.tsx","kind":"import-statement","original":"./routes/login/index.tsx"},{"path":"app/routes/home/index.tsx","kind":"import-statement","original":"./routes/home/index.tsx"},{"path":"app/routes/$username.tsx","kind":"import-statement","original":"./routes/$username.tsx"},{"path":"app/routes/logout.tsx","kind":"import-statement","original":"./routes/logout.tsx"},{"path":"app/routes/error.tsx","kind":"import-statement","original":"./routes/error.tsx"},{"path":"app/routes/index.tsx","kind":"import-statement","original":"./routes/index.tsx"},{"path":"server-assets-manifest:@remix-run/dev/assets-manifest","kind":"import-statement","original":"@remix-run/dev/assets-manifest"}],"format":"esm"},"<stdin>":{"bytes":44,"imports":[{"path":"server-entry-module:@remix-run/dev/server-build","kind":"import-statement","original":"@remix-run/dev/server-build"}],"format":"esm"}},"outputs":{"api/_assets/tailwind-RC5S45OF.css":{"imports":[],"exports":[],"inputs":{"app/tailwind.css":{"bytesInOutput":11727}},"bytes":11727},"api/index.js.map":{"imports":[],"exports":[],"inputs":{},"bytes":64955},"api/index.js":{"imports":[{"path":"node:stream","kind":"require-call","external":true},{"path":"@remix-run/node","kind":"require-call","external":true},{"path":"@remix-run/react","kind":"require-call","external":true},{"path":"isbot","kind":"require-call","external":true},{"path":"react-dom/server","kind":"require-call","external":true},{"path":"react/jsx-dev-runtime","kind":"require-call","external":true},{"path":"@remix-run/react","kind":"require-call","external":true},{"path":"api/_assets/tailwind-RC5S45OF.css","kind":"file-loader"},{"path":"react/jsx-dev-runtime","kind":"require-call","external":true},{"path":"react","kind":"require-call","external":true},{"path":"react/jsx-dev-runtime","kind":"require-call","external":true},{"path":"@remix-run/node","kind":"require-call","external":true},{"path":"@remix-run/react","kind":"require-call","external":true},{"path":"react-dom","kind":"require-call","external":true},{"path":"react","kind":"require-call","external":true},{"path":"@remix-run/react","kind":"require-call","external":true},{"path":"react/jsx-dev-runtime","kind":"require-call","external":true},{"path":"@prisma/client","kind":"require-call","external":true},{"path":"react/jsx-dev-runtime","kind":"require-call","external":true},{"path":"react","kind":"require-call","external":true},{"path":"react/jsx-dev-runtime","kind":"require-call","external":true},{"path":"@remix-run/react","kind":"require-call","external":true},{"path":"@remix-run/node","kind":"require-call","external":true},{"path":"@remix-run/node","kind":"require-call","external":true},{"path":"bcryptjs","kind":"require-call","external":true},{"path":"bcryptjs","kind":"require-call","external":true},{"path":"react/jsx-dev-runtime","kind":"require-call","external":true},{"path":"react/jsx-dev-runtime","kind":"require-call","external":true},{"path":"@remix-run/node","kind":"require-call","external":true},{"path":"react","kind":"require-call","external":true},{"path":"@remix-run/react","kind":"require-call","external":true},{"path":"react/jsx-dev-runtime","kind":"require-call","external":true},{"path":"@remix-run/node","kind":"require-call","external":true},{"path":"@remix-run/node","kind":"require-call","external":true},{"path":"@remix-run/react","kind":"require-call","external":true},{"path":"tailwindcss/colors","kind":"require-call","external":true},{"path":"react/jsx-dev-runtime","kind":"require-call","external":true},{"path":"@remix-run/node","kind":"require-call","external":true},{"path":"@remix-run/node","kind":"require-call","external":true},{"path":"@remix-run/node","kind":"require-call","external":true},{"path":"@remix-run/react","kind":"require-call","external":true},{"path":"react/jsx-dev-runtime","kind":"require-call","external":true},{"path":"react-icons/ri","kind":"require-call","external":true},{"path":"react/jsx-dev-runtime","kind":"require-call","external":true}],"exports":[],"entryPoint":"<stdin>","inputs":{"<stdin>":{"bytesInOutput":294},"app/entry.server.tsx":{"bytesInOutput":3025},"app/root.tsx":{"bytesInOutput":2215},"app/tailwind.css":{"bytesInOutput":63},"app/routes/login/components/form-field.tsx":{"bytesInOutput":1844},"app/routes/home/link.$linkId.tsx":{"bytesInOutput":813},"app/components/home/portal.tsx":{"bytesInOutput":788},"app/components/home/modal.tsx":{"bytesInOutput":1604},"app/utils/prisma.server.ts":{"bytesInOutput":166},"app/utils/link.server.ts":{"bytesInOutput":427},"app/routes/login/index.tsx":{"bytesInOutput":9871},"app/components/layout.tsx":{"bytesInOutput":394},"app/utils/auth.server.ts":{"bytesInOutput":3266},"app/utils/user.server.ts":{"bytesInOutput":866},"app/utils/validators.server.ts":{"bytesInOutput":1795},"app/components/logo.tsx":{"bytesInOutput":528},"app/routes/home/index.tsx":{"bytesInOutput":9085},"app/routes/$username.tsx":{"bytesInOutput":3291},"app/routes/logout.tsx":{"bytesInOutput":261},"app/routes/error.tsx":{"bytesInOutput":175},"app/routes/index.tsx":{"bytesInOutput":4423},"app/components/sign-out-button.tsx":{"bytesInOutput":757},"server-assets-manifest:@remix-run/dev/assets-manifest":{"bytesInOutput":3220},"server-entry-module:@remix-run/dev/server-build":{"bytesInOutput":1869}},"bytes":53518}}}